dipperpy/__init__.py
dipperpy/base.py
dipperpy/missing.py
dipperpy/plasma.py
dipperpy/version.py
dipperpy/lightspinner/__init__.py
dipperpy/lightspinner/atmosphere.py
dipperpy/lightspinner/atomic_model.py
dipperpy/lightspinner/atomic_set.py
dipperpy/lightspinner/atomic_table.py
dipperpy/lightspinner/background.py
dipperpy/lightspinner/collisional_rates.py
dipperpy/lightspinner/constants.py
dipperpy/lightspinner/fal.py
dipperpy/lightspinner/formal_solver.py
dipperpy/lightspinner/multi.py
dipperpy/lightspinner/radtransfer_spectrum.py
dipperpy/lightspinner/response_fn.py
dipperpy/lightspinner/rh_atoms_model.py
dipperpy/lightspinner/rh_method.py
dipperpy/lightspinner/utils.py
dipperpy/lightspinner/witt.py
dipperpy/lightspinner/xdrlib.py
dipperpy-1.0.6.dist-info/licenses/LICENSE
dipperpy-1.0.6.dist-info/METADATA
dipperpy-1.0.6.dist-info/WHEEL
dipperpy-1.0.6.dist-info/top_level.txt
dipperpy-1.0.6.dist-info/RECORD
