Metadata-Version: 2.4
Name: dipperpy
Version: 1.0.6
Summary: Package performing spectral diagnostics and radiative transfer calculations
Author-email: "Philip G. Judge" <judge@ucar.edu>
Maintainer-email: "Maurice L. Wilson" <mauricew@ucar.edu>
License-Expression: MIT
Project-URL: repository, https://github.com/MWilson1/dipperpy
Project-URL: Curriculum Vitae, https://www.mauricewilson.com
Keywords: solar,astrophysics,radiative transfer,spectroscopy
Classifier: Programming Language :: Python :: 3
Classifier: Operating System :: OS Independent
Classifier: Intended Audience :: Science/Research
Classifier: Intended Audience :: Developers
Classifier: Programming Language :: Python
Classifier: Topic :: Scientific/Engineering
Classifier: Topic :: Scientific/Engineering :: Physics
Requires-Python: >=3.0
License-File: LICENSE
Dynamic: license-file
